{
    "pagocuotas": [
        {
            "field": "id",
            "name": "Id"
        },
        {
            "field": "legajo",
            "name": "Legajo"
        },
        {
            "field": "nroCuota",
            "name": "Numero de Cuotas"
        },
        {
            "field": "monto",
            "name": "Monto"
        },
        {
            "field": "nroRecibo",
            "name": "Numero de Recibo"
        },
        {
            "field": "fechaCarga",
            "name": "Fecha de Carga"
        },
        {
            "field": "fechaRecibo",
            "name": "Fecha de Recibo"
        }
    ]
}